crawler.py
sbcrawler.py
sbcrawler-0.1.2.dist-info/LICENSE
sbcrawler-0.1.2.dist-info/METADATA
sbcrawler-0.1.2.dist-info/WHEEL
sbcrawler-0.1.2.dist-info/top_level.txt
sbcrawler-0.1.2.dist-info/RECORD
