Metadata-Version: 2.1
Name: sbcrawler
Version: 0.1.2
Summary: A light weight crawler
Home-page: https://github.com/ffteen/sbcrawler
Author: ffteen
Author-email: ffteen@qq.com
License: UNKNOWN
Platform: UNKNOWN
Requires-Dist: tornado
Requires-Dist: requests
Requires-Dist: requests-html
